st_stylish/StyleInjector.py
st_stylish/__init__.py
st_stylish/helpers.py
st_stylish/iframe/__init__.py
st_stylish-1.0.0.dist-info/LICENSE
st_stylish-1.0.0.dist-info/METADATA
st_stylish-1.0.0.dist-info/WHEEL
st_stylish-1.0.0.dist-info/top_level.txt
st_stylish-1.0.0.dist-info/RECORD
