Metadata-Version: 2.1
Name: st-stylish
Version: 1.0.0
Summary: A collection of custom components and helper functions for Streamlit that are focused on providing advanced styling functionality.
Author-email: Kellen Busby Software LLC <kellenbusby@gmail.com>
License: GNU GENERAL PUBLIC LICENSE
Classifier: License :: OSI Approved :: GNU General Public License v3 or later (GPLv3+)
Classifier: Programming Language :: Python
Classifier: Programming Language :: Python :: 3
Requires-Python: >=3.8
License-File: LICENSE
Requires-Dist: streamlit (>=0.63)
